langua/__init__.py
langua/detector.py
langua/detector_factory.py
langua/lang_detect_exception.py
langua/langua_check.py
langua/language.py
langua/predict_lang.py
langua/profiles/af
langua/profiles/ar
langua/profiles/bg
langua/profiles/bn
langua/profiles/ca
langua/profiles/cs
langua/profiles/cy
langua/profiles/da
langua/profiles/de
langua/profiles/el
langua/profiles/en
langua/profiles/es
langua/profiles/et
langua/profiles/fa
langua/profiles/fi
langua/profiles/fr
langua/profiles/gu
langua/profiles/he
langua/profiles/hi
langua/profiles/hr
langua/profiles/hu
langua/profiles/id
langua/profiles/it
langua/profiles/ja
langua/profiles/kn
langua/profiles/ko
langua/profiles/lt
langua/profiles/lv
langua/profiles/mk
langua/profiles/ml
langua/profiles/mr
langua/profiles/ne
langua/profiles/nl
langua/profiles/no
langua/profiles/pa
langua/profiles/pl
langua/profiles/pt
langua/profiles/ro
langua/profiles/ru
langua/profiles/sk
langua/profiles/sl
langua/profiles/so
langua/profiles/sq
langua/profiles/sv
langua/profiles/sw
langua/profiles/ta
langua/profiles/te
langua/profiles/th
langua/profiles/tl
langua/profiles/tr
langua/profiles/uk
langua/profiles/ur
langua/profiles/vi
langua/profiles/zh-cn
langua/profiles/zh-tw
langua/tests/__init__.py
langua/utils/__init__.py
langua/utils/lang_profile.py
langua/utils/messages.properties
langua/utils/messages.py
langua/utils/ngram.py
langua/utils/unicode_block.py
langua-1.0.11.dist-info/DESCRIPTION.rst
langua-1.0.11.dist-info/METADATA
langua-1.0.11.dist-info/RECORD
langua-1.0.11.dist-info/WHEEL
langua-1.0.11.dist-info/metadata.json
langua-1.0.11.dist-info/top_level.txt
