Metadata-Version: 2.0
Name: langua
Version: 1.0.11
Summary: Faster port of Language detection built by Shuyo in Python
Home-page: https://github.com/whiletruelearn/langua
Author: Krishna Sangeeth KS
Author-email: kskrishnasangeeth@gmail.com
License:    Licensed under the Apache License, Version 2.0 (the "License");
Requires-Dist: numpy
Requires-Dist: six
